{
  "updated_at": "2026-06-17T14:21:04+09:00",
  "auto_generated": true,
  "source": "Gemini AI自動分析（Reuters/BBC/Al Jazeera RSS）",
  "scenario": {
    "A_diplomacy_pct": 85,
    "B_partial_blockade_pct": 10,
    "C_full_blockade_pct": 0,
    "D_escalation_pct": 5
  },
  "hormuz_daily_flow_mbpd": 10.0,
  "hormuz_normal_flow_mbpd": 21.0,
  "flow_disruption_pct": 52,
  "critical_date": "2026-04-24",
  "critical_note": "米イラン停戦合意の正式署名",
  "last_manual_note": "米イランが停戦合意に達し、ホルムズ海峡の封鎖解除が開始。原油価格は下落する一方、合意詳細や正式署名待ちで不確実性も残る。",
  "ais_estimated_vessels": 25,
  "ais_estimated_tankers": 10,
  "ais_estimated_cargo": 15,
  "ais_estimation_note": "ニュース報道より推計(medium)"
}